bmb_message_content_types/__init__.py
bmb_message_content_types/version.py
bmb_message_content_types-0.0.2.dist-info/METADATA
bmb_message_content_types-0.0.2.dist-info/WHEEL
bmb_message_content_types-0.0.2.dist-info/top_level.txt
bmb_message_content_types-0.0.2.dist-info/RECORD
