Metadata-Version: 2.1
Name: bmb-message-content-types
Version: 0.0.2
Summary: Bmbix message content types
Home-page: https://dev.bmbix.com
Author: Robin Abbi
Author-email: robin.abbi@downley.net
License: Proprietary.
Keywords: bmb
Platform: UNKNOWN
